repodepo/__init__.py
repodepo/_version.py
repodepo/initscript_postgres.sql
repodepo/initscript_sqlite.sql
repodepo/misc.py
repodepo/repo_database.py
repodepo/data/botlist.csv
repodepo/data/filters/filtered_packageedges.csv
repodepo/data/filters/filtered_packages.csv
repodepo/data/filters/filtered_repoedges.csv
repodepo/data/filters/filtered_repos.csv
repodepo/extras/__init__.py
repodepo/extras/anonymization.py
repodepo/extras/errors.py
repodepo/extras/exports.py
repodepo/extras/ghtorrent_stats.py
repodepo/extras/home.py
repodepo/extras/stats.py
repodepo/fillers/__init__.py
repodepo/fillers/bot_fillers.py
repodepo/fillers/commit_info.py
repodepo/fillers/crates.py
repodepo/fillers/deps_filters_fillers.py
repodepo/fillers/filler.py
repodepo/fillers/generic.py
repodepo/fillers/github_gql.py
repodepo/fillers/github_rest.py
repodepo/fillers/gitlab_gql.py
repodepo/fillers/julia.py
repodepo/fillers/meta_fillers.py
repodepo/fillers/snowball.py
repodepo/getters/SR_getters.py
repodepo/getters/__init__.py
repodepo/getters/bot_checks.py
repodepo/getters/combined_getters.py
repodepo/getters/edge_getters.py
repodepo/getters/effect_rank_getters.py
repodepo/getters/generic_getters.py
repodepo/getters/policy_getters.py
repodepo/getters/project_getters.py
repodepo/getters/rank_getters.py
repodepo/getters/user_getters.py
repodepo-0.1.3.dist-info/LICENSE
repodepo-0.1.3.dist-info/METADATA
repodepo-0.1.3.dist-info/WHEEL
repodepo-0.1.3.dist-info/top_level.txt
repodepo-0.1.3.dist-info/RECORD
