Metadata-Version: 2.1
Name: repodepo
Version: 0.1.3
Summary: Set of tools to build datasets about repositories
Home-page: https://github.com/wschuell/repodepo
Author: William Schueller
Author-email: 
License: GNU AFFERO GENERAL PUBLIC LICENSE Version 3
Platform: UNKNOWN
Requires-Dist: gql[all] (>=0.0.dev0)
Requires-Dist: pygit2
Requires-Dist: pygithub
Requires-Dist: pandas
Requires-Dist: psycopg2-binary
Requires-Dist: pytest-timeout
Requires-Dist: gitpython
Requires-Dist: oyaml
Requires-Dist: scipy
Requires-Dist: sh
Requires-Dist: psutil
Requires-Dist: python-dateutil
Requires-Dist: networkx
Requires-Dist: semantic-version
